n_const/__init__.py
n_const/constants.py
n_const/data_format.py
n_const/deprecated.py
n_const/obsparams.py
n_const/pointing.py
n_const-1.1.0.dist-info/LICENSE
n_const-1.1.0.dist-info/WHEEL
n_const-1.1.0.dist-info/METADATA
n_const-1.1.0.dist-info/RECORD
