Metadata-Version: 2.1
Name: n-const
Version: 1.1.0
Summary: Necst Constants and ObservatioN Specification Translator.
Home-page: https://nanten2.github.io/N-CONST
License: MIT
Author: KaoruNishikawa
Author-email: k.nishikawa@a.phys.nagoya-u.ac.jp
Requires-Python: >=3.6,<4.0
Classifier: License :: OSI Approved :: MIT License
Classifier: Programming Language :: Python :: 3
Classifier: Programming Language :: Python :: 3.10
Classifier: Programming Language :: Python :: 3.6
Classifier: Programming Language :: Python :: 3.7
Classifier: Programming Language :: Python :: 3.8
Classifier: Programming Language :: Python :: 3.9
Requires-Dist: astropy (>=3.0,<4.0); python_version < "3.8"
Requires-Dist: astropy (>=5.0.4,<6.0.0); python_version >= "3.8"
Requires-Dist: dataclasses (>=0.8,<0.9); python_version >= "3.6" and python_version < "3.7"
Requires-Dist: numpy (>=1.19,<2.0)
Requires-Dist: tomlkit (>=0.10,<0.11)
Requires-Dist: typing-extensions (>=3.0,<5.0); python_version < "3.9"
Project-URL: Repository, https://github.com/nanten2/N-CONST
